spotted/__init__.py
spotted/_base_client.py
spotted/_client.py
spotted/_compat.py
spotted/_constants.py
spotted/_exceptions.py
spotted/_files.py
spotted/_models.py
spotted/_qs.py
spotted/_resource.py
spotted/_response.py
spotted/_streaming.py
spotted/_types.py
spotted/_version.py
spotted/pagination.py
spotted/py.typed
spotted/_utils/__init__.py
spotted/_utils/_compat.py
spotted/_utils/_datetime_parse.py
spotted/_utils/_json.py
spotted/_utils/_logs.py
spotted/_utils/_proxy.py
spotted/_utils/_reflection.py
spotted/_utils/_resources_proxy.py
spotted/_utils/_streams.py
spotted/_utils/_sync.py
spotted/_utils/_transform.py
spotted/_utils/_typing.py
spotted/_utils/_utils.py
spotted/lib/.keep
spotted/resources/__init__.py
spotted/resources/albums.py
spotted/resources/artists.py
spotted/resources/audio_analysis.py
spotted/resources/audio_features.py
spotted/resources/audiobooks.py
spotted/resources/chapters.py
spotted/resources/episodes.py
spotted/resources/markets.py
spotted/resources/recommendations.py
spotted/resources/search.py
spotted/resources/shows.py
spotted/resources/tracks.py
spotted/resources/browse/__init__.py
spotted/resources/browse/browse.py
spotted/resources/browse/categories.py
spotted/resources/me/__init__.py
spotted/resources/me/albums.py
spotted/resources/me/audiobooks.py
spotted/resources/me/episodes.py
spotted/resources/me/following.py
spotted/resources/me/me.py
spotted/resources/me/playlists.py
spotted/resources/me/shows.py
spotted/resources/me/top.py
spotted/resources/me/tracks.py
spotted/resources/me/player/__init__.py
spotted/resources/me/player/player.py
spotted/resources/me/player/queue.py
spotted/resources/playlists/__init__.py
spotted/resources/playlists/followers.py
spotted/resources/playlists/images.py
spotted/resources/playlists/playlists.py
spotted/resources/playlists/tracks.py
spotted/resources/users/__init__.py
spotted/resources/users/playlists.py
spotted/resources/users/users.py
spotted/types/__init__.py
spotted-0.26.0.dist-info/METADATA
spotted-0.26.0.dist-info/WHEEL
spotted-0.26.0.dist-info/licenses/LICENSE
spotted-0.26.0.dist-info/RECORD
